pycard.cpython-313-aarch64-linux-gnu.so
pysolvers.cpython-313-aarch64-linux-gnu.so
pysat/__init__.py
pysat/_fileio.py
pysat/_utils.py
pysat/card.py
pysat/engines.py
pysat/formula.py
pysat/pb.py
pysat/process.py
pysat/solvers.py
pysat/allies/__init__.py
pysat/allies/approxmc.py
pysat/allies/unigen.py
pysat/examples/__init__.py
pysat/examples/bbscan.py
pysat/examples/bica.py
pysat/examples/fm.py
pysat/examples/genhard.py
pysat/examples/hitman.py
pysat/examples/lbx.py
pysat/examples/lsu.py
pysat/examples/mcsls.py
pysat/examples/models.py
pysat/examples/musx.py
pysat/examples/optux.py
pysat/examples/primer.py
pysat/examples/rc2.py
pysat/examples/usage.py
python_sat-1.8.dev26.data/scripts/approxmc.py
python_sat-1.8.dev26.data/scripts/bbscan.py
python_sat-1.8.dev26.data/scripts/bica.py
python_sat-1.8.dev26.data/scripts/fm.py
python_sat-1.8.dev26.data/scripts/genhard.py
python_sat-1.8.dev26.data/scripts/lbx.py
python_sat-1.8.dev26.data/scripts/lsu.py
python_sat-1.8.dev26.data/scripts/mcsls.py
python_sat-1.8.dev26.data/scripts/models.py
python_sat-1.8.dev26.data/scripts/musx.py
python_sat-1.8.dev26.data/scripts/optux.py
python_sat-1.8.dev26.data/scripts/primer.py
python_sat-1.8.dev26.data/scripts/rc2.py
python_sat-1.8.dev26.data/scripts/unigen.py
python_sat-1.8.dev26.dist-info/METADATA
python_sat-1.8.dev26.dist-info/WHEEL
python_sat-1.8.dev26.dist-info/top_level.txt
python_sat-1.8.dev26.dist-info/RECORD
python_sat-1.8.dev26.dist-info/licenses/LICENSE.txt
