Metadata-Version: 2.4
Name: python-sat
Version: 1.8.dev26
Summary: A Python library for prototyping with SAT oracles
Home-page: https://github.com/pysathq/pysat
Author: Alexey Ignatiev, Joao Marques-Silva, Antonio Morgado
Author-email: alexey.ignatiev@monash.edu, joao.marques-silva@univ-toulouse.fr, ajrmorgado@gmail.com
License: MIT
License-File: LICENSE.txt
Requires-Dist: six
Provides-Extra: aiger
Requires-Dist: py-aiger-cnf>=2.0.0; extra == "aiger"
Provides-Extra: approxmc
Requires-Dist: pyapproxmc>=4.1.8; extra == "approxmc"
Provides-Extra: cryptosat
Requires-Dist: pycryptosat>=5.11.18; extra == "cryptosat"
Provides-Extra: pblib
Requires-Dist: pypblib>=0.0.3; extra == "pblib"
Provides-Extra: unigen
Requires-Dist: pyunigen>=4.1.20; extra == "unigen"
Dynamic: author
Dynamic: author-email
Dynamic: description
Dynamic: description-content-type
Dynamic: home-page
Dynamic: license
Dynamic: license-file
Dynamic: provides-extra
Dynamic: requires-dist
Dynamic: summary
